__init__.py
mathplug.py
test_mathplug.py
mathplug-0.0.3.dist-info/LICENSE.md
mathplug-0.0.3.dist-info/METADATA
mathplug-0.0.3.dist-info/WHEEL
mathplug-0.0.3.dist-info/top_level.txt
mathplug-0.0.3.dist-info/RECORD
