Metadata-Version: 2.1
Name: mathplug
Version: 0.0.3
Summary: A lightweight Python package which supplies simple math functions.
Home-page: https://github.com/JordanWelsman/mathplug/
Author: Jordan Welsman
Author-email: jordan.welsman@outlook.com
Classifier: Development Status :: 2 - Pre-Alpha
Classifier: Intended Audience :: Other Audience
Classifier: License :: OSI Approved :: MIT License
Classifier: Operating System :: OS Independent
Classifier: Programming Language :: Python :: 3.9
Classifier: Topic :: Scientific/Engineering :: Mathematics
License-File: LICENSE.md
Provides-Extra: dev
Requires-Dist: pytest (>=7.1) ; extra == 'dev'
